{"status":"done","chunks":{"devextreme":[{"name":"devextreme.js","path":"C:\\Users\\АСЕР\\Desktop\\Archive\\Archive.WebUI\\wwwroot\\bundles\\js\\devextreme.js"}],"main":[{"name":"main.js","path":"C:\\Users\\АСЕР\\Desktop\\Archive\\Archive.WebUI\\wwwroot\\bundles\\js\\main.js"}],"vendors":[{"name":"vendors.js","path":"C:\\Users\\АСЕР\\Desktop\\Archive\\Archive.WebUI\\wwwroot\\bundles\\js\\vendors.js"}]},"error":"ModuleNotFoundError","message":"Module not found: Error: Can't resolve '../layouts/SingleCard-card' in 'C:\\Users\\АСЕР\\Desktop\\Archive\\Archive.WebUI\\client-app\\src\\router'"}